miprimo/miprimo.py
miprimo-1.0.dist-info/LICENSE
miprimo-1.0.dist-info/METADATA
miprimo-1.0.dist-info/WHEEL
miprimo-1.0.dist-info/top_level.txt
miprimo-1.0.dist-info/RECORD
