Metadata-Version: 2.1
Name: miprimo
Version: 1.0
Summary: A tool to obtain prime numbers to n.
Home-page: UNKNOWN
Author: Francisco José Gálvez Palomo
Author-email: fgalvez@gmail.com
License: GNU GPLv3
Keywords: pyoperaciones mathematical operations primos primo
Platform: UNKNOWN
Classifier: Development Status :: 4 - Beta
Classifier: Intended Audience :: Developers
Classifier: Topic :: Utilities
Classifier: License :: OSI Approved :: GNU General Public License v3 (GPLv3)
Classifier: Programming Language :: Python :: 3
Classifier: Operating System :: OS Independent
License-File: LICENSE
